{"cameraMode":{"drawMode":0,"name":"Shaded","section":"Shading Mode"},"sceneLighting":true,"audioPlay":false,"sceneViewState":{"m_AlwaysRefresh":false,"showFog":true,"showSkybox":true,"showFlares":true,"showImageEffects":true,"showParticleSystems":true,"showVisualEffectGraphs":true,"m_FxEnabled":true},"in2DMode":false,"pivot":{"x":233.80581665039063,"y":-49.07231521606445,"z":-13.278481483459473},"rotation":{"x":0.11382201313972473,"y":0.6785011887550354,"z":-0.10752048343420029,"w":0.717841625213623},"size":89.82479095458985,"orthographic":false}