{"cameraMode":{"drawMode":0,"name":"Shaded","section":"Shading Mode"},"sceneLighting":true,"audioPlay":false,"sceneViewState":{"m_AlwaysRefresh":false,"showFog":true,"showSkybox":true,"showFlares":true,"showImageEffects":true,"showParticleSystems":true,"showVisualEffectGraphs":true,"m_FxEnabled":true},"in2DMode":false,"pivot":{"x":0.8437991738319397,"y":3.4278557300567629,"z":1.523686170578003},"rotation":{"x":-0.051004670560359958,"y":0.20963600277900697,"z":0.010950139723718167,"w":0.9763916730880737},"size":10.449999809265137,"orthographic":false}